[
  {
    "ชื่อพัสดุ": "Analgesic cream:30g",
    "ว.ป.ด.": "19 ก.ค. 65",
    "หลักฐาน": "TQ65/02887/1",
    "Lot.no.": "265592",
    "ราคาทุน": 10.63,
    "รับ": 0,
    "จ่าย": 300,
    "คงเหลือ": 66116,
    "ราคารวม": 702818.08,
    "ลงชื่อ": "-",
    "หมายเหตุ": "-"
  },
  {
    "ชื่อพัสดุ": "Analgesic cream:30g",
    "ว.ป.ด.": "19 ก.ค. 65",
    "หลักฐาน": "TQ65/02896/1",
    "Lot.no.": "265592",
    "ราคาทุน": 10.63,
    "รับ": 0,
    "จ่าย": 200,
    "คงเหลือ": 65916,
    "ราคารวม": 700687.08,
    "ลงชื่อ": "-",
    "หมายเหตุ": "-"
  },
  {
    "ชื่อพัสดุ": "Analgesic cream:30g",
    "ว.ป.ด.": "19 ก.ค. 65",
    "หลักฐาน": "TQ65/02906/1",
    "Lot.no.": "265592",
    "ราคาทุน": 10.63,
    "รับ": 0,
    "จ่าย": 1800,
    "คงเหลือ": 64116,
    "ราคารวม": 681553.08,
    "ลงชื่อ": "-",
    "หมายเหตุ": "-"
  },
  {
    "ชื่อพัสดุ": "Analgesic cream:30g",
    "ว.ป.ด.": "19 ก.ค. 65",
    "หลักฐาน": "TQ65/02907/1",
    "Lot.no.": "265592",
    "ราคาทุน": 10.63,
    "รับ": 0,
    "จ่าย": 684,
    "คงเหลือ": 63432,
    "ราคารวม": 674282.16,
    "ลงชื่อ": "-",
    "หมายเหตุ": "-"
  },
  {
    "ชื่อพัสดุ": "Analgesic cream:30g",
    "ว.ป.ด.": "19 ก.ค. 65",
    "หลักฐาน": "TQ65/02907/1",
    "Lot.no.": "265603",
    "ราคาทุน": 10.63,
    "รับ": 0,
    "จ่าย": 4316,
    "คงเหลือ": 59116,
    "ราคารวม": 628403.08,
    "ลงชื่อ": "-",
    "หมายเหตุ": "-"
  },
  {
    "ชื่อพัสดุ": "Analgesic cream:30g",
    "ว.ป.ด.": "19 ก.ค. 65",
    "หลักฐาน": "TQ65/02909/1",
    "Lot.no.": "265603",
    "ราคาทุน": 10.63,
    "รับ": 0,
    "จ่าย": 40,
    "คงเหลือ": 59076,
    "ราคารวม": 627977.88,
    "ลงชื่อ": "-",
    "หมายเหตุ": "-"
  },
  {
    "ชื่อพัสดุ": "Analgesic cream:30g",
    "ว.ป.ด.": "19 ก.ค. 65",
    "หลักฐาน": "IN65/01606",
    "Lot.no.": "265593",
    "ราคาทุน": 10.594,
    "รับ": 10594,
    "จ่าย": 0,
    "คงเหลือ": 69670,
    "ราคารวม": 740592.1,
    "ลงชื่อ": "-",
    "หมายเหตุ": "-"
  }
]