[
  {
    "ชื่อพัสดุ": "Analgesic cream:30g",
    "ว.ป.ด.": "1 ก.พ. 66",
    "หลักฐาน": "XQ66/00264/1",
    "Lot.no.": "266360",
    "ราคาทุน": 11.53,
    "รับ": 0,
    "จ่าย": 11385,
    "คงเหลือ": 20715,
    "ราคารวม": 238843.95,
    "ลงชื่อ": "-",
    "หมายเหตุ": "เบิกยาส่งให้คนไข้กรมแพทย์ทหารบก"
  },
  {
    "ชื่อพัสดุ": "Analgesic cream:30g",
    "ว.ป.ด.": "1 ก.พ. 66",
    "หลักฐาน": "XQ66/00264/1",
    "Lot.no.": "266362",
    "ราคาทุน": 11.53,
    "รับ": 0,
    "จ่าย": 7241,
    "คงเหลือ": 13474,
    "ราคารวม": 155355.22,
    "ลงชื่อ": "-",
    "หมายเหตุ": "เบิกยาส่งให้คนไข้กรมแพทย์ทหารบก"
  },
  {
    "ชื่อพัสดุ": "Analgesic cream:30g",
    "ว.ป.ด.": "4 ก.พ. 66",
    "หลักฐาน": "TQ66/03087/1",
    "Lot.no.": "266336",
    "ราคาทุน": 11.53,
    "รับ": 0,
    "จ่าย": 800,
    "คงเหลือ": 12674,
    "ราคารวม": 146131.22,
    "ลงชื่อ": "-",
    "หมายเหตุ": "คุณ จามย์ แซ่ขุนทด จ.กรุงเทพ"
  },
  {
    "ชื่อพัสดุ": "Analgesic cream:30g",
    "ว.ป.ด.": "4 ก.พ. 66",
    "หลักฐาน": "TQ66/03093/1",
    "Lot.no.": "266336",
    "ราคาทุน": 11.53,
    "รับ": 0,
    "จ่าย": 1000,
    "คงเหลือ": 11674,
    "ราคารวม": 134606.22,
    "ลงชื่อ": "-",
    "หมายเหตุ": "โรงพยาบาลธรรมศาสตร์ ที่ 1400414566"
  },
  {
    "ชื่อพัสดุ": "Analgesic cream:30g",
    "ว.ป.ด.": "4 ก.พ. 66",
    "หลักฐาน": "TQ66/03096/1",
    "Lot.no.": "266336",
    "ราคาทุน": 11.53,
    "รับ": 0,
    "จ่าย": 4000,
    "คงเหลือ": 7674,
    "ราคารวม": 88481.22,
    "ลงชื่อ": "-",
    "หมายเหตุ": "รพ.ค่ายกฤษณ์สีวะระ จ.สกลนคร"
  },
  {
    "ชื่อพัสดุ": "Analgesic cream:30g",
    "ว.ป.ด.": "7 ก.พ. 66",
    "หลักฐาน": "TQ66/03116/1",
    "Lot.no.": "266336",
    "ราคาทุน": 11.53,
    "รับ": 0,
    "จ่าย": 200,
    "คงเหลือ": 7474,
    "ราคารวม": 86175.22,
    "ลงชื่อ": "-",
    "หมายเหตุ": "สถานทีแห่งแส้ง ผลิตภัณฑ์โรงงานเกสส์กรรมธรรมชาติ (ตรีมิตร) ที่ PO230906-01"
  },
  {
    "ชื่อพัสดุ": "Analgesic cream:30g",
    "ว.ป.ด.": "11 ก.พ. 66",
    "หลักฐาน": "IN66/01636",
    "Lot.no.": "266150",
    "ราคาทุน": 11.53,
    "รับ": 19,
    "จ่าย": 0,
    "คงเหลือ": 7493,
    "ราคารวม": 86394.29,
    "ลงชื่อ": "-",
    "หมายเหตุ": "SR66/00041"
  },
  {
    "ชื่อพัสดุ": "Analgesic cream:30g",
    "ว.ป.ด.": "11 ก.พ. 66",
    "หลักฐาน": "TQ66/03140/1",
    "Lot.no.": "266336",
    "ราคาทุน": 11.53,
    "รับ": 0,
    "จ่าย": 500,
    "คงเหลือ": 6993,
    "ราคารวม": 80629.29,
    "ลงชื่อ": "-",
    "หมายเหตุ": "รพ.ค่ายทศพรศรีสุทน จ.นครศรีธรรมราช"
  },
  {
    "ชื่อพัสดุ": "Analgesic cream:30g",
    "ว.ป.ด.": "11 ก.พ. 66",
    "หลักฐาน": "TQ66/02922/1",
    "Lot.no.": "266336",
    "ราคาทุน": 11.53,
    "รับ": 0,
    "จ่าย": 379,
    "คงเหลือ": 6614,
    "ราคารวม": 76259.42,
    "ลงชื่อ": "-",
    "หมายเหตุ": "กองบัญชาการตำรวจตระเวนชายแดน ที่ บช.732/66083"
  },
  {
    "ชื่อพัสดุ": "Analgesic cream:30g",
    "ว.ป.ด.": "11 ก.พ. 66",
    "หลักฐาน": "TQ66/02922/1",
    "Lot.no.": "266359",
    "ราคาทุน": 11.53,
    "รับ": 0,
    "จ่าย": 311,
    "คงเหลือ": 6303,
    "ราคารวม": 72673.59,
    "ลงชื่อ": "-",
    "หมายเหตุ": "กองบัญชาการตำรวจตระเวนชายแดน ที่ บช.732/66083"
  }
]