[
  {
    "ชื่อพัสดุ": "Pseudoephedrine HCl 30mg/5ml syrup : 60 ml",
    "ว.ป.ด.": "10 มิ.ย. 68",
    "หลักฐาน": "XQ68/00200/1",
    "Lot.no.": "968725",
    "ราคาทุน": 10.1,
    "รับ": 0,
    "จ่าย": 30,
    "คงเหลือ": 179073,
    "ราคารวม": 1824753.8,
    "ลงชื่อ": "-",
    "หมายเหตุ": "เพื่อเป็นยาตัวอย่าง Pseudoephedrine HCl syrup สล4/2567 งวดที่ 2 ครั้งที่ 1"
  },
  {
    "ชื่อพัสดุ": "Pseudoephedrine HCl 30mg/5ml syrup : 60 ml",
    "ว.ป.ด.": "10 มิ.ย. 68",
    "หลักฐาน": "XQ68/00200/1",
    "Lot.no.": "968726",
    "ราคาทุน": 10.1,
    "รับ": 0,
    "จ่าย": 30,
    "คงเหลือ": 179043,
    "ราคารวม": 1824448.17,
    "ลงชื่อ": "-",
    "หมายเหตุ": "เพื่อเป็นยาตัวอย่าง Pseudoephedrine HCl syrup สล4/2567 งวดที่ 2 ครั้งที่ 1"
  },
  {
    "ชื่อพัสดุ": "Pseudoephedrine HCl 30mg/5ml syrup : 60 ml",
    "ว.ป.ด.": "10 มิ.ย. 68",
    "หลักฐาน": "XQ68/00200/1",
    "Lot.no.": "968727",
    "ราคาทุน": 10.1,
    "รับ": 0,
    "จ่าย": 30,
    "คงเหลือ": 179013,
    "ราคารวม": 1824142.47,
    "ลงชื่อ": "-",
    "หมายเหตุ": "เพื่อเป็นยาตัวอย่าง Pseudoephedrine HCl syrup สล4/2567 งวดที่ 2 ครั้งที่ 1"
  },
  {
    "ชื่อพัสดุ": "Pseudoephedrine HCl 30mg/5ml syrup : 60 ml",
    "ว.ป.ด.": "10 มิ.ย. 68",
    "หลักฐาน": "XQ68/00200/1",
    "Lot.no.": "968728",
    "ราคาทุน": 10.1,
    "รับ": 0,
    "จ่าย": 30,
    "คงเหลือ": 178983,
    "ราคารวม": 1823836.77,
    "ลงชื่อ": "-",
    "หมายเหตุ": "เพื่อเป็นยาตัวอย่าง Pseudoephedrine HCl syrup สล4/2567 งวดที่ 2 ครั้งที่ 1"
  },
  {
    "ชื่อพัสดุ": "Pseudoephedrine HCl 30mg/5ml syrup : 60 ml",
    "ว.ป.ด.": "10 มิ.ย. 68",
    "หลักฐาน": "TQ68/02333/1",
    "Lot.no.": "968709",
    "ราคาทุน": 10.1,
    "รับ": 0,
    "จ่าย": 8161,
    "คงเหลือ": 170822,
    "ราคารวม": 1725302.2,
    "ลงชื่อ": "-",
    "หมายเหตุ": "สำนักงานคณะกรรมการอาหารและยา (กลุ่มเงินทุนหมุนเวียนยาเสพติด) ที่ สล4/2567 (งวดที่ 1 ครั้งที่ 5)"
  }
]