[
  {
    "ชื่อพัสดุ": "Pseudoephedrine HCl Powder (จัดซื้อ)",
    "ว.ป.ด.": "14 ต.ค. 68",
    "หลักฐาน": "WF68/01252/1",
    "Lot.no.": "515925",
    "ราคาทุน": 2.41525256,
    "รับ": 0,
    "จ่าย": 30000,
    "คงเหลือ": 27381,
    "ราคารวม": 66132.03,
    "ลงชื่อ": "-",
    "หมายเหตุ": "Pseudoephedrine HCl 60 mg Tablet : 100 x 10's"
  },
  {
    "ชื่อพัสดุ": "Pseudoephedrine HCl Powder (จัดซื้อ)",
    "ว.ป.ด.": "17 ต.ค. 68",
    "หลักฐาน": "WF68/01320/1",
    "Lot.no.": "515925",
    "ราคาทุน": 2.41525256,
    "รับ": 0,
    "จ่าย": 2402,
    "คงเหลือ": 24979,
    "ราคารวม": 60330.59,
    "ลงชื่อ": "-",
    "หมายเหตุ": "Pseudoephedrine HCl 30mg/5ml syrup : 60 ml"
  },
  {
    "ชื่อพัสดุ": "Pseudoephedrine HCl Powder (จัดซื้อ)",
    "ว.ป.ด.": "17 ต.ค. 68",
    "หลักฐาน": "WF68/01320/1",
    "Lot.no.": "506325",
    "ราคาทุน": 2.4381028,
    "รับ": 0,
    "จ่าย": 598,
    "คงเหลือ": 24381,
    "ราคารวม": 59443.38,
    "ลงชื่อ": "-",
    "หมายเหตุ": "Pseudoephedrine HCl 30mg/5ml syrup : 60 ml"
  },
  {
    "ชื่อพัสดุ": "Pseudoephedrine HCl Powder (จัดซื้อ)",
    "ว.ป.ด.": "17 ต.ค. 68",
    "หลักฐาน": "WF68/01321/1",
    "Lot.no.": "506325",
    "ราคาทุน": 2.4381028,
    "รับ": 0,
    "จ่าย": 3000,
    "คงเหลือ": 21381,
    "ราคารวม": 52129.08,
    "ลงชื่อ": "-",
    "หมายเหตุ": "Pseudoephedrine HCl 30mg/5ml syrup : 60 ml"
  },
  {
    "ชื่อพัสดุ": "Pseudoephedrine HCl Powder (จัดซื้อ)",
    "ว.ป.ด.": "17 ต.ค. 68",
    "หลักฐาน": "WF68/01322/1",
    "Lot.no.": "506325",
    "ราคาทุน": 2.4381028,
    "รับ": 0,
    "จ่าย": 3000,
    "คงเหลือ": 18381,
    "ราคารวม": 44814.77,
    "ลงชื่อ": "-",
    "หมายเหตุ": "Pseudoephedrine HCl 30mg/5ml syrup : 60 ml"
  },
  {
    "ชื่อพัสดุ": "Pseudoephedrine HCl Powder (จัดซื้อ)",
    "ว.ป.ด.": "17 ต.ค. 68",
    "หลักฐาน": "WF68/01323/1",
    "Lot.no.": "506325",
    "ราคาทุน": 2.4381028,
    "รับ": 0,
    "จ่าย": 3000,
    "คงเหลือ": 15381,
    "ราคารวม": 37500.46,
    "ลงชื่อ": "-",
    "หมายเหตุ": "Pseudoephedrine HCl 30mg/5ml syrup : 60 ml"
  },
  {
    "ชื่อพัสดุ": "Pseudoephedrine HCl Powder (จัดซื้อ)",
    "ว.ป.ด.": "17 ต.ค. 68",
    "หลักฐาน": "WF68/01324/1",
    "Lot.no.": "506325",
    "ราคาทุน": 2.4381028,
    "รับ": 0,
    "จ่าย": 3000,
    "คงเหลือ": 12381,
    "ราคารวม": 30186.15,
    "ลงชื่อ": "-",
    "หมายเหตุ": "Pseudoephedrine HCl 30mg/5ml syrup : 60 ml"
  },
  {
    "ชื่อพัสดุ": "Pseudoephedrine HCl Powder (จัดซื้อ)",
    "ว.ป.ด.": "17 ต.ค. 68",
    "หลักฐาน": "WF68/01325/1",
    "Lot.no.": "506325",
    "ราคาทุน": 2.4381028,
    "รับ": 0,
    "จ่าย": 3000,
    "คงเหลือ": 9381,
    "ราคารวม": 22871.84,
    "ลงชื่อ": "-",
    "หมายเหตุ": "Pseudoephedrine HCl 30mg/5ml syrup : 60 ml"
  }
]