[
  {
    "ชื่อพัสดุ": "Pseudoephedrine HCl 30mg/5ml syrup : 60 ml",
    "ว.ป.ด.": "13 ส.ค. 67",
    "หลักฐาน": "IN67/01622",
    "Lot.no.": "967651",
    "ราคาทุน": 9.91,
    "รับ": 7996,
    "จ่าย": 0,
    "คงเหลือ": 178663,
    "ราคารวม": 1770550.33,
    "ลงชื่อ": "-",
    "หมายเหตุ": "PK67/00979/1"
  },
  {
    "ชื่อพัสดุ": "Pseudoephedrine HCl 30mg/5ml syrup : 60 ml",
    "ว.ป.ด.": "14 ส.ค. 67",
    "หลักฐาน": "XQ67/00268/1",
    "Lot.no.": "967626",
    "ราคาทุน": 9.91,
    "รับ": 0,
    "จ่าย": 30,
    "คงเหลือ": 178633,
    "ราคารวม": 1770253.03,
    "ลงชื่อ": "-",
    "หมายเหตุ": "เพื่อเป็นยาตด. Pseudo syr สด 3/2566 งวด 5 ครั้ง 2"
  },
  {
    "ชื่อพัสดุ": "Pseudoephedrine HCl 30mg/5ml syrup : 60 ml",
    "ว.ป.ด.": "14 ส.ค. 67",
    "หลักฐาน": "XQ67/00268/1",
    "Lot.no.": "967625",
    "ราคาทุน": 9.91,
    "รับ": 0,
    "จ่าย": 30,
    "คงเหลือ": 178603,
    "ราคารวม": 1769955.73,
    "ลงชื่อ": "-",
    "หมายเหตุ": "เพื่อเป็นยาตด. Pseudo syr สด 3/2566 งวด 5 ครั้ง 2"
  },
  {
    "ชื่อพัสดุ": "Pseudoephedrine HCl 30mg/5ml syrup : 60 ml",
    "ว.ป.ด.": "14 ส.ค. 67",
    "หลักฐาน": "XQ67/00268/1",
    "Lot.no.": "967628",
    "ราคาทุน": 9.91,
    "รับ": 0,
    "จ่าย": 30,
    "คงเหลือ": 178573,
    "ราคารวม": 1769658.43,
    "ลงชื่อ": "-",
    "หมายเหตุ": "เพื่อเป็นยาตด. Pseudo syr สด 3/2566 งวด 5 ครั้ง 2"
  },
  {
    "ชื่อพัสดุ": "Pseudoephedrine HCl 30mg/5ml syrup : 60 ml",
    "ว.ป.ด.": "14 ส.ค. 67",
    "หลักฐาน": "XQ67/00268/1",
    "Lot.no.": "967627",
    "ราคาทุน": 9.91,
    "รับ": 0,
    "จ่าย": 30,
    "คงเหลือ": 178543,
    "ราคารวม": 1769361.13,
    "ลงชื่อ": "-",
    "หมายเหตุ": "เพื่อเป็นยาตด. Pseudo syr สด 3/2566 งวด 5 ครั้ง 2"
  },
  {
    "ชื่อพัสดุ": "Pseudoephedrine HCl 30mg/5ml syrup : 60 ml",
    "ว.ป.ด.": "14 ส.ค. 67",
    "หลักฐาน": "XQ67/00268/1",
    "Lot.no.": "967629",
    "ราคาทุน": 9.91,
    "รับ": 0,
    "จ่าย": 30,
    "คงเหลือ": 178513,
    "ราคารวม": 1769063.83,
    "ลงชื่อ": "-",
    "หมายเหตุ": "เพื่อเป็นยาตด. Pseudo syr สด 3/2566 งวด 5 ครั้ง 2"
  },
  {
    "ชื่อพัสดุ": "Pseudoephedrine HCl 30mg/5ml syrup : 60 ml",
    "ว.ป.ด.": "15 ส.ค. 67",
    "หลักฐาน": "TQ67/02866/1",
    "Lot.no.": "967630",
    "ราคาทุน": 9.91,
    "รับ": 0,
    "จ่าย": 8031,
    "คงเหลือ": 170482,
    "ราคารวม": 1689476.62,
    "ลงชื่อ": "-",
    "หมายเหตุ": "สำนักงานคณะกรรรมการอาหารและยา (กลุ่มเงินทุนหมุนเวียนยาเสพติด) ที่ สด 3/2566 (งวดที่ 5 ครั้งที่ 3)"
  }
]